[{"id":"PLAVjA4WVof5bXt9ypiapltV-WiHOp4H8Z","title":"\"SPILLER SOM..\"","thumbnail":"https:\/\/i.ytimg.com\/vi\/CqGdvHA1QP4\/mqdefault.jpg"},{"id":"PLAVjA4WVof5YEN94v4HnW8iRQpfjJDFGr","title":"Top 5 Plays of The Month","thumbnail":"https:\/\/i.ytimg.com\/vi\/DOiGSd91RMI\/mqdefault.jpg"},{"id":"PLAVjA4WVof5b-wfOTfJbxIgqH4eHAkG9k","title":"PANORAMA UI","thumbnail":"https:\/\/i.ytimg.com\/vi\/A9n5TfYhfxE\/mqdefault.jpg"},{"id":"PLAVjA4WVof5bj5pVuWyU5KGWkjbv4WKw2","title":"FRA SILVER TIL GLOBAL","thumbnail":"https:\/\/i.ytimg.com\/vi\/v0b46D-4Roo\/mqdefault.jpg"},{"id":"PLAVjA4WVof5Z6yr0cBoVIOaMftvnRG3Je","title":"CS:GO Challenges","thumbnail":"https:\/\/i.ytimg.com\/vi\/c7Kop1xnXmc\/mqdefault.jpg"},{"id":"PLAVjA4WVof5YW6sTVwkwX2xvu1HdR5vnN","title":"TWITCH HIGHLIGHTS","thumbnail":"https:\/\/i.ytimg.com\/vi\/QJdG7xZOD1g\/mqdefault.jpg"},{"id":"PLAVjA4WVof5ZqLR0JfxiZadKP-rKXoF42","title":"Juleferie 2016 \/ Kjasper 10K special","thumbnail":"https:\/\/i.ytimg.com\/vi\/sTL-VdADtiE\/mqdefault.jpg"},{"id":"PLAVjA4WVof5ZXyklujE947WSMttHZf9j9","title":"CS:GO STRAT ROULETTE","thumbnail":"https:\/\/i.ytimg.com\/vi\/x0QBmL17IvY\/mqdefault.jpg"},{"id":"PLAVjA4WVof5YtdfK67KcyZb--bJtyw-z6","title":"AFSL\u00d8RER HACKERS I CS:GO","thumbnail":"https:\/\/i.ytimg.com\/vi\/unWSiWljHzI\/mqdefault.jpg"},{"id":"PLAVjA4WVof5ZmxRXV7S5yDJK43z4ux2y1","title":"CS:GO Competitive","thumbnail":"https:\/\/i.ytimg.com\/vi\/LBwy0zeo524\/mqdefault.jpg"},{"id":"PLAVjA4WVof5ZjKUG5xsQJtbmjrjBClprZ","title":"CS:GO FUNNY MOMENTS","thumbnail":"https:\/\/i.ytimg.com\/vi\/D8dmg6DOqEc\/mqdefault.jpg"},{"id":"PLAVjA4WVof5bHcABszMIu9B0-EqMs58zb","title":"Cassiopea UHC S\u00e6son 6","thumbnail":"https:\/\/i.ytimg.com\/vi\/j_vLfp-7UxA\/mqdefault.jpg"},{"id":"PLAVjA4WVof5bjVTBJ_8lmk5DCqjCqRE4C","title":"Cassiopea UHC S\u00e6son 5","thumbnail":"https:\/\/i.ytimg.com\/vi\/TPTaSGwWyWU\/mqdefault.jpg"},{"id":"PLAVjA4WVof5aPRI-VHCskOkZjjXDuetAL","title":"Cassiopea UHC S\u00e6son 4","thumbnail":"https:\/\/i.ytimg.com\/vi\/XwGYVgSTl9U\/mqdefault.jpg"},{"id":"PLAVjA4WVof5YkUhwT7LC9RUopO0QlP5X0","title":"\u00c8n Chance SMP","thumbnail":"https:\/\/i.ytimg.com\/vi\/lfAufqhqCHI\/mqdefault.jpg"},{"id":"PLAVjA4WVof5bfBsBkO05NfidU93M2-WDm","title":"Captive MInecraft II med Bisse","thumbnail":"https:\/\/i.ytimg.com\/vi\/6VVNa8bSZcI\/mqdefault.jpg"},{"id":"PLAVjA4WVof5ajOUZyjgT4S2K1tuIyuJq7","title":"Captive Minecraft IV","thumbnail":"https:\/\/i.ytimg.com\/vi\/Q7fFf2B-H8E\/mqdefault.jpg"},{"id":"PLAVjA4WVof5bsHgx56fReQ0blXnJcgRvn","title":"Friheden","thumbnail":"https:\/\/i.ytimg.com\/vi\/m87NQgUdt-4\/mqdefault.jpg"},{"id":"PLAVjA4WVof5alLYAoI4lSMq_ZaD91SNga","title":"Kortfilm","thumbnail":"https:\/\/i.ytimg.com\/vi\/qQYW1zrGAqA\/mqdefault.jpg"},{"id":"PLAVjA4WVof5Y5xE72HQfC4iD8jEECgUpb","title":"IRL VIDEOER","thumbnail":"https:\/\/i.ytimg.com\/vi\/qQYW1zrGAqA\/mqdefault.jpg"},{"id":"PLAVjA4WVof5Y3ALLK4v6krv_nR0c2OfXV","title":"Vlogs","thumbnail":"https:\/\/i.ytimg.com\/vi\/BbNXVWb-vOw\/mqdefault.jpg"},{"id":"PLAVjA4WVof5atMMVZ3fh0W6O97zSK5g5W","title":"SG Veteranen","thumbnail":"https:\/\/i.ytimg.com\/vi\/uSB0SVv7D3Y\/mqdefault.jpg"},{"id":"PLAVjA4WVof5a-cfPkqjs7lwtclHbNne9O","title":"LeQuest SMP","thumbnail":"https:\/\/i.ytimg.com\/vi\/iEYH3xWE4cU\/mqdefault.jpg"},{"id":"PLAVjA4WVof5ZzkmaZPqRS1k6H4DASni_I","title":"Cassiopea SMP S5","thumbnail":"https:\/\/i.ytimg.com\/vi\/hXWeLALmj8c\/mqdefault.jpg"},{"id":"PLAVjA4WVof5ZebXVq4LXJeaHfXTXet_ZY","title":"Cassiopea UHC S\u00c6SON 3","thumbnail":"https:\/\/i.ytimg.com\/vi\/U2xkS2xV5Eg\/mqdefault.jpg"},{"id":"PLAVjA4WVof5b2Y-IkxQAoyFxa_A9GMSPK","title":"Cassiopea SMP S\u00e6son 4","thumbnail":"https:\/\/i.ytimg.com\/vi\/exh3mj7NB7o\/mqdefault.jpg"},{"id":"PLAVjA4WVof5bIFfXikpUsSGCMQNuKcSU4","title":"Goat Simulator!","thumbnail":"https:\/\/i.ytimg.com\/vi\/TdKNTPKZcnY\/mqdefault.jpg"},{"id":"PLAVjA4WVof5auv48BIgMYuEc5JjN3pKu6","title":"Cassiopea SMP S\u00c6SON 3","thumbnail":"https:\/\/i.ytimg.com\/vi\/M0pIyo_Nj5Y\/mqdefault.jpg"},{"id":"PLAVjA4WVof5a1NBJf5SSnxjtFk6RQDn61","title":"Cassiopea UHC S\u00c6SON 2","thumbnail":"https:\/\/i.ytimg.com\/vi\/JDdtU-wiCKw\/mqdefault.jpg"},{"id":"PLAVjA4WVof5avYlFAGIA7Mvkmyy9Bw8bd","title":"Cassiopea UHC S\u00c6SON 1","thumbnail":"https:\/\/i.ytimg.com\/vi\/5_4OjKEFfLg\/mqdefault.jpg"},{"id":"PLAVjA4WVof5beOYxN4hrvONih5C_bpcjR","title":"Minecraft Survival Games","thumbnail":"https:\/\/i.ytimg.com\/vi\/nQ8NpGE3Qms\/mqdefault.jpg"}]